README.rst
setup.py
bmtools/__init__.py
bmtools/bmtools.py
bmtools/objects.py
bmtools/utils.py
bmtools.egg-info/PKG-INFO
bmtools.egg-info/SOURCES.txt
bmtools.egg-info/dependency_links.txt
bmtools.egg-info/requires.txt
bmtools.egg-info/top_level.txt